centernet/__init__.py
centernet/config.py
centernet/data/custom_build_augmentation.py
centernet/data/custom_dataset_dataloader.py
centernet/data/datasets/coco.py
centernet/data/datasets/nuimages.py
centernet/data/datasets/objects365.py
centernet/data/transforms/custom_augmentation_impl.py
centernet/data/transforms/custom_transform.py
centernet/modeling/debug.py
centernet/modeling/backbone/bifpn.py
centernet/modeling/backbone/bifpn_fcos.py
centernet/modeling/backbone/dla.py
centernet/modeling/backbone/dlafpn.py
centernet/modeling/backbone/fpn_p5.py
centernet/modeling/backbone/res2net.py
centernet/modeling/dense_heads/centernet.py
centernet/modeling/dense_heads/centernet_head.py
centernet/modeling/dense_heads/utils.py
centernet/modeling/layers/deform_conv.py
centernet/modeling/layers/heatmap_focal_loss.py
centernet/modeling/layers/iou_loss.py
centernet/modeling/layers/ml_nms.py
centernet/modeling/meta_arch/centernet_detector.py
centernet/modeling/roi_heads/custom_fast_rcnn.py
centernet/modeling/roi_heads/custom_roi_heads.py
centernet/modeling/roi_heads/fed_loss.py
centernet2-1.0.post20221121.dist-info/LICENSE
centernet2-1.0.post20221121.dist-info/METADATA
centernet2-1.0.post20221121.dist-info/WHEEL
centernet2-1.0.post20221121.dist-info/top_level.txt
centernet2-1.0.post20221121.dist-info/RECORD
