Metadata-Version: 2.1
Name: centernet2
Version: 1.0.post20221121
Summary: CenterNet2 python package
Home-page: https://github.com/xingyizhou/CenterNet2
License-File: LICENSE
Requires-Dist: opencv-python
Provides-Extra: dev
Requires-Dist: pytest ; extra == 'dev'
